HarmonyDecoder/__init__.py
HarmonyDecoder/drawing.py
HarmonyDecoder/function.py
HarmonyDecoder/harmony.py
HarmonyDecoder/interval.py
HarmonyDecoder/logger.py
HarmonyDecoder/note.py
HarmonyDecoder/possiblenotes.py
HarmonyDecoder/program.py
HarmonyDecoder/rules.py
HarmonyDecoder/scale.py
HarmonyDecoder/setup.py
HarmonyDecoder/strdecoder.py
HarmonyDecoder/ui.py
HarmonyDecoder/Images/BassCleff.png
HarmonyDecoder/Images/Flat.png
HarmonyDecoder/Images/Icon.png
HarmonyDecoder/Images/Sharp.png
HarmonyDecoder/Images/TrebleCleff.png
HarmonyDecoder-1.0.9.dist-info/LICENSE
HarmonyDecoder-1.0.9.dist-info/METADATA
HarmonyDecoder-1.0.9.dist-info/WHEEL
HarmonyDecoder-1.0.9.dist-info/top_level.txt
HarmonyDecoder-1.0.9.dist-info/RECORD
