Metadata-Version: 2.1
Name: HarmonyDecoder
Version: 1.0.9
Summary: HarmonyDecoder package
Author-email: Przemysław Kojs <przemek.kojs@gmail.com>
Maintainer-email: Przemysław Kojs <przemek.kojs@gmail.com>
License: GNU GENERAL PUBLIC LICENSE
Keywords: harmony,music,notes,decoder,parser
Classifier: Programming Language :: Python :: 3
Classifier: License :: OSI Approved :: GNU General Public License (GPL)
Classifier: Operating System :: OS Independent
Requires-Python: >=3.7
License-File: LICENSE
Requires-Dist: pyqt5
Provides-Extra: gui
Requires-Dist: PyQt5 ; extra == 'gui'
